genSearch/__init__.py
genSearch/algorithms.py
genSearch/constants.py
genSearch/helperFunctions.py
genSearch/interface.py
genSearch-0.0.10.dist-info/LICENSE
genSearch-0.0.10.dist-info/METADATA
genSearch-0.0.10.dist-info/WHEEL
genSearch-0.0.10.dist-info/top_level.txt
genSearch-0.0.10.dist-info/RECORD
