Metadata-Version: 2.1
Name: genSearch
Version: 0.0.10
Summary: A genetic search algorithm
Author: Federico Barrera
Author-email: fede.j.ba10@gmail.com
Classifier: Programming Language :: Python :: 3
Classifier: License :: OSI Approved :: MIT License
Classifier: Operating System :: OS Independent
Requires-Python: >=3.10
License-File: LICENSE
Requires-Dist: numpy
